t2iadapter/__init__.py
t2iadapter/version.py
t2iadapter/adapters/__init__.py
t2iadapter/adapters/coadapters.py
t2iadapter/adapters/t2i_adapters_for_canny.py
t2iadapter/adapters/t2i_adapters_for_style.py
t2iadapter/ldm/__init__.py
t2iadapter/ldm/inference_base.py
t2iadapter/ldm/lr_scheduler.py
t2iadapter/ldm/util.py
t2iadapter/ldm/data/__init__.py
t2iadapter/ldm/data/dataset_coco.py
t2iadapter/ldm/data/dataset_depth.py
t2iadapter/ldm/data/dataset_laion.py
t2iadapter/ldm/data/dataset_wikiart.py
t2iadapter/ldm/data/utils.py
t2iadapter/ldm/models/__init__.py
t2iadapter/ldm/models/autoencoder.py
t2iadapter/ldm/models/diffusion/__init__.py
t2iadapter/ldm/models/diffusion/ddim.py
t2iadapter/ldm/models/diffusion/ddpm.py
t2iadapter/ldm/models/diffusion/plms.py
t2iadapter/ldm/models/diffusion/dpm_solver/__init__.py
t2iadapter/ldm/models/diffusion/dpm_solver/dpm_solver.py
t2iadapter/ldm/models/diffusion/dpm_solver/sampler.py
t2iadapter/ldm/modules/__init__.py
t2iadapter/ldm/modules/attention.py
t2iadapter/ldm/modules/ema.py
t2iadapter/ldm/modules/diffusionmodules/__init__.py
t2iadapter/ldm/modules/diffusionmodules/model.py
t2iadapter/ldm/modules/diffusionmodules/openaimodel.py
t2iadapter/ldm/modules/diffusionmodules/util.py
t2iadapter/ldm/modules/distributions/__init__.py
t2iadapter/ldm/modules/distributions/distributions.py
t2iadapter/ldm/modules/encoders/__init__.py
t2iadapter/ldm/modules/encoders/adapter.py
t2iadapter/ldm/modules/encoders/modules.py
t2iadapter/ldm/modules/extra_condition/__init__.py
t2iadapter/ldm/modules/extra_condition/api.py
t2iadapter/ldm/modules/extra_condition/model_edge.py
t2iadapter/ldm/modules/extra_condition/utils.py
t2iadapter/ldm/modules/extra_condition/midas/__init__.py
t2iadapter/ldm/modules/extra_condition/midas/api.py
t2iadapter/ldm/modules/extra_condition/midas/utils.py
t2iadapter/ldm/modules/extra_condition/midas/midas/__init__.py
t2iadapter/ldm/modules/extra_condition/midas/midas/base_model.py
t2iadapter-0.1.3.dist-info/LICENSE
t2iadapter-0.1.3.dist-info/METADATA
t2iadapter-0.1.3.dist-info/WHEEL
t2iadapter-0.1.3.dist-info/top_level.txt
t2iadapter-0.1.3.dist-info/RECORD
