Metadata-Version: 2.1
Name: t2iadapter
Version: 0.1.3
Summary: T2I-Adapter
Home-page: https://github.com/TencentARC/T2I-Adapter
Author: TencentARC
Author-email: arc@tencent.com
License: Apache License 2.0
Keywords: computer vision
Platform: UNKNOWN
Classifier: Development Status :: 4 - Beta
Classifier: License :: OSI Approved :: Apache Software License
Classifier: Operating System :: OS Independent
Classifier: Programming Language :: Python :: 3
Classifier: Programming Language :: Python :: 3.7
Classifier: Programming Language :: Python :: 3.8
Requires-Dist: transformers (==4.19.2)
Requires-Dist: diffusers (==0.11.1)
Requires-Dist: invisible-watermark (==0.1.5)
Requires-Dist: basicsr (==1.4.2)
Requires-Dist: einops (==0.6.0)
Requires-Dist: omegaconf (==2.3.0)
Requires-Dist: pytorch-lightning (==1.5.9)
Requires-Dist: kornia (==0.6.8)
Requires-Dist: gradio
Requires-Dist: opencv-python
Requires-Dist: pudb
Requires-Dist: imageio
Requires-Dist: imageio-ffmpeg
Requires-Dist: k-diffusion
Requires-Dist: webdataset
Requires-Dist: open-clip-torch
Requires-Dist: kornia
Requires-Dist: safetensors
Requires-Dist: timm
Requires-Dist: openmim
Requires-Dist: mmpose
Requires-Dist: mmdet
